{
  "code": 200,
  "msg": "ok",
  "data": {
    "data": [
      {
        "code": "16102003",
        "name": "进口泰国龙眼1kg",
        "spec": "1kg",
        "warehousename": "成品仓",
        "expiredate": "2017-11-07",
        "expiredaynum": "5",
        "warningdate": "2017-11-05",
        "warningdaynum": "3",
        "productiondate": "2017-11-02",
        "stocknum": "19",
        "type": "expired",
        "remainExpireDays": -50
      },
      {
        "code": "16203005",
        "name": "四川丹棱爱媛橘橙1kg",
        "spec": "1kg装",
        "warehousename": "成品仓",
        "expiredate": "2017-11-20",
        "expiredaynum": "7",
        "warningdate": "2017-11-17",
        "warningdaynum": "4",
        "productiondate": "2017-11-13",
        "stocknum": "46",
        "type": "expired",
        "remainExpireDays": -37
      },
      {
        "code": "16204008",
        "name": "平和琯溪蜜柚（白肉）两粒装",
        "spec": "2粒装\/单果2斤以上",
        "warehousename": "成品仓",
        "expiredate": "2017-11-28",
        "expiredaynum": "15",
        "warningdate": "2017-11-21",
        "warningdaynum": "8",
        "productiondate": "2017-11-13",
        "stocknum": "30",
        "type": "expired",
        "remainExpireDays": -29
      },
      {
        "code": "16301005",
        "name": "新疆阿克苏苹果5kg\/单果80mm-85mm",
        "spec": "单果80mm-85mm",
        "warehousename": "成品仓",
        "expiredate": "2017-11-24",
        "expiredaynum": "15",
        "warningdate": "2017-11-17",
        "warningdaynum": "8",
        "productiondate": "2017-11-09",
        "stocknum": "2",
        "type": "expired",
        "remainExpireDays": -33
      },
      {
        "code": "16302003",
        "name": "皇冠梨6个\/单果250g-280g",
        "spec": "6个\/单果250g-280g",
        "warehousename": "中转仓",
        "expiredate": "2017-11-23",
        "expiredaynum": "15",
        "warningdate": "2017-11-16",
        "warningdaynum": "8",
        "productiondate": "2017-11-08",
        "stocknum": "9",
        "type": "expired",
        "remainExpireDays": -34
      },
      {
        "code": "16709008",
        "name": "四川蒲江红心猕猴桃12个\/单果85g-110g",
        "spec": "12个\/单果80g以上",
        "warehousename": "中转仓",
        "expiredate": "2017-11-17",
        "expiredaynum": "15",
        "warningdate": "2017-11-10",
        "warningdaynum": "8",
        "productiondate": "2017-11-02",
        "stocknum": "8",
        "type": "expired",
        "remainExpireDays": -40
      },
      {
        "code": "16709009",
        "name": "翠香猕猴桃12个\/单果80g以上",
        "spec": "单果80g以上",
        "warehousename": "成品仓",
        "expiredate": "2017-11-28",
        "expiredaynum": "15",
        "warningdate": "2017-11-21",
        "warningdaynum": "8",
        "productiondate": "2017-11-13",
        "stocknum": "2",
        "type": "expired",
        "remainExpireDays": -29
      },
      {
        "code": "16710002",
        "name": "进口越南红心火龙果2个\/单果450g",
        "spec": "2个\/单果450g",
        "warehousename": "成品仓",
        "expiredate": "2017-10-16",
        "expiredaynum": "7",
        "warningdate": "2017-10-13",
        "warningdaynum": "4",
        "productiondate": "2017-10-09",
        "stocknum": "2",
        "type": "expired",
        "remainExpireDays": -72
      },
      {
        "code": "21601001",
        "name": "芦花鸡白凤乌骨鸡",
        "spec": "700g\/袋",
        "warehousename": "成品仓",
        "expiredate": "2018-02-23",
        "expiredaynum": "360",
        "warningdate": "2017-08-27",
        "warningdaynum": "180",
        "productiondate": "2017-02-28",
        "stocknum": "10",
        "type": "warning",
        "remainExpireDays": 59
      },
      {
        "code": "21601006",
        "name": "易盛玖灰芦花鸡翅根1000g",
        "spec": "1000g\/袋",
        "warehousename": "成品仓",
        "expiredate": "2018-03-06",
        "expiredaynum": "360",
        "warningdate": "2017-09-07",
        "warningdaynum": "180",
        "productiondate": "2017-03-11",
        "stocknum": "21",
        "type": "warning",
        "remainExpireDays": 70
      }
    ],
    "totalCount": 89,
    "totalPage": 9
  }
}
